codefest/cf04/hdl/mac_correct.v
`timescale 1ns/1ps

module mac (
    input  logic             clk,
    input  logic             rst,
    input  logic signed [7:0]  a,
    input  logic signed [7:0]  b,
    output wire  signed [31:0] out
);

    logic signed [31:0] acc_reg;

    always_ff @(posedge clk) begin
        if (rst)
            acc_reg <= 32'sd0;
        else
            acc_reg <= acc_reg + (a * b);
    end

    assign out = acc_reg;

endmodule

codefest/cf04/cocotb_mac/sim_build/dump.vcd
$version Generated by VerilatedVcd $end
$timescale 1ps $end
 $scope module $rootio $end
  $var wire 1 " clk $end
  $var wire 1 # rst $end
  $var wire 8 $ a [7:0] $end
  $var wire 8 % b [7:0] $end
  $var wire 32 & out [31:0] $end
 $upscope $end
 $scope module mac $end
  $var wire 1 ' clk $end
  $var wire 1 ( rst $end
  $var wire 8 ) a [7:0] $end
  $var wire 8 * b [7:0] $end
  $var wire 32 + out [31:0] $end
  $var wire 32 , acc_reg [31:0] $end
 $upscope $end
$enddefinitions $end


#0
1"
1#
b00000000 $
b00000000 %
b00000000000000000000000000000000 &
1'
1(
b00000000 )
b00000000 *
b00000000000000000000000000000000 +
b00000000000000000000000000000000 ,
#1000
0#
b00000011 $
b00000100 %
0(
b00000011 )
b00000100 *
#5000
0"
0'
#10000
1"
b00000000000000000000000000001100 &
1'
b00000000000000000000000000001100 +
b00000000000000000000000000001100 ,
#15000
0"
0'
#20000
1"
b00000000000000000000000000011000 &
1'
b00000000000000000000000000011000 +
b00000000000000000000000000011000 ,
#25000
0"
0'
#30000
1"
b00000000000000000000000000100100 &
1'
b00000000000000000000000000100100 +
b00000000000000000000000000100100 ,
#31000
1#
1(
#35000
0"
0'
#40000
1"
b00000000000000000000000000000000 &
1'
b00000000000000000000000000000000 +
b00000000000000000000000000000000 ,
#41000
0#
b11111011 $
b00000010 %
0(
b11111011 )
b00000010 *
#45000
0"
0'
#50000
1"
b11111111111111111111111111110110 &
1'
b11111111111111111111111111110110 +
b11111111111111111111111111110110 ,
#55000
0"
0'
#60000
1"
b11111111111111111111111111101100 &
1'
b11111111111111111111111111101100 +
b11111111111111111111111111101100 ,
